ai_cap_utils/__init__.py
ai_cap_utils/state.py
ai_cap_utils/type.py
ai_cap_utils/version.py
ai_cap_utils/agent/__init__.py
ai_cap_utils/agent/_base.py
ai_cap_utils/agent/base.py
ai_cap_utils/agent/prebuilt.py
ai_cap_utils/streamlit/__init__.py
ai_cap_utils/streamlit/utils.py
ai_cap_utils/tool/__init__.py
ai_cap_utils/tool/prebuilt.py
ai_cap_utils/utils/__init__.py
ai_cap_utils/utils/envcreds.py
ai_cap_utils-0.5.0.dist-info/METADATA
ai_cap_utils-0.5.0.dist-info/WHEEL
ai_cap_utils-0.5.0.dist-info/RECORD
