Metadata-Version: 2.4
Name: ai-cap-utils
Version: 0.5.0
Summary: A utilities library for Common AI Platform
Author-email: Anupong Wannakrairot <anuponwa@scg.com>
Requires-Python: >=3.11
Requires-Dist: coolname>=2.2.0
Requires-Dist: dotenv>=0.9.9
Requires-Dist: langchain-anthropic>=0.3.10
Requires-Dist: langchain-community>=0.3.21
Requires-Dist: langchain-google-vertexai>=2.0.20
Requires-Dist: langchain-openai>=0.3.12
Requires-Dist: langchain>=0.3.23
Requires-Dist: langgraph>=0.3.29
Requires-Dist: streamlit>=1.44.1
